hhhhhhhhs.py
hhhhhhhscraping-0.0.1.dist-info/LICENSE.txt
hhhhhhhscraping-0.0.1.dist-info/METADATA
hhhhhhhscraping-0.0.1.dist-info/WHEEL
hhhhhhhscraping-0.0.1.dist-info/top_level.txt
hhhhhhhscraping-0.0.1.dist-info/RECORD
