Metadata-Version: 2.2
Name: hhhhhhhscraping
Version: 0.0.1
Summary: hhhhhhhhhhk
Author-email: hhhhhhh <hhhhhhh@gmail.com>
License: MIT License
Classifier: Programming Language :: Python :: 3
Classifier: Operating System :: OS Independent
Requires-Python: >=3.10
License-File: LICENSE.txt
Requires-Dist: requests>=4.13.3
Requires-Dist: pandas>=2.2.3
Requires-Dist: beautifulsoup4>=2.32.3
